kpds_pkg/__init__.py
kpds_pkg/config.py
kpds_pkg/kpds_api.py
kpds_pkg-1.0.dist-info/METADATA
kpds_pkg-1.0.dist-info/WHEEL
kpds_pkg-1.0.dist-info/top_level.txt
kpds_pkg-1.0.dist-info/RECORD
