Metadata-Version: 2.1
Name: kpds-pkg
Version: 1.0
Summary: Data Feeding API Service
Home-page: https://github.com/koreapds/kpds_package
Author: KoreaPDS
Author-email: koreapds@koreapds.com
License: UNKNOWN
Download-URL: https://github.com/koreapds/kpds_package/archive/master.zip
Keywords: kpds_api,kpds_pkg,kpds
Platform: UNKNOWN
Classifier: Programming Language :: Python :: 3
Classifier: Programming Language :: Python :: 3.2
Classifier: Programming Language :: Python :: 3.3
Classifier: Programming Language :: Python :: 3.4
Classifier: Programming Language :: Python :: 3.5
Classifier: Programming Language :: Python :: 3.6
Classifier: Programming Language :: Python :: 3.7
Requires-Python: >=3
Requires-Dist: requests
Requires-Dist: pandas
